gsa_pytorch/__init__.py
gsa_pytorch/gsa_pytorch.py
gsa_pytorch-0.2.2.dist-info/LICENSE
gsa_pytorch-0.2.2.dist-info/METADATA
gsa_pytorch-0.2.2.dist-info/WHEEL
gsa_pytorch-0.2.2.dist-info/top_level.txt
gsa_pytorch-0.2.2.dist-info/RECORD
