Metadata-Version: 2.1
Name: gsa-pytorch
Version: 0.2.2
Summary: Global Self-attention Network (GSA) - Pytorch
Home-page: https://github.com/lucidrains/global-self-attention-network
Author: Phil Wang
Author-email: lucidrains@gmail.com
License: MIT
Keywords: artificial intelligence,attention mechanism,image recognition
Platform: UNKNOWN
Classifier: Development Status :: 4 - Beta
Classifier: Intended Audience :: Developers
Classifier: Topic :: Scientific/Engineering :: Artificial Intelligence
Classifier: License :: OSI Approved :: MIT License
Classifier: Programming Language :: Python :: 3.6
Requires-Dist: torch (>=1.6)
Requires-Dist: einops (>=0.3)
